psycopg2_pool/__init__.py
psycopg2_pool-1.0.dist-info/LICENSE
psycopg2_pool-1.0.dist-info/METADATA
psycopg2_pool-1.0.dist-info/WHEEL
psycopg2_pool-1.0.dist-info/top_level.txt
psycopg2_pool-1.0.dist-info/RECORD
